setup.cfg
setup.py
minipoker/__init__.py
minipoker.egg-info/PKG-INFO
minipoker.egg-info/SOURCES.txt
minipoker.egg-info/dependency_links.txt
minipoker.egg-info/top_level.txt
minipoker/gui/__init__.py
minipoker/gui/game.py
minipoker/logic/__init__.py
minipoker/logic/deck.py
minipoker/logic/hands.py
minipoker/logic/players.py
minipoker/logic/poker.py
minipoker/logic/tests.py
minipoker/logic/ai/__init__.py
minipoker/logic/ai/aiplayers.py
minipoker/logic/ai/strategies.py
minipoker/logic/ai/utils.py