Metadata-Version: 1.1
Name: minipoker
Version: 0.0.3
Summary: Poker Game
Home-page: https://github.com/reutsharabani/minipoker
Author: Reut Sharabani
Author-email: reut.sharabani@gmail.com
License: MIT
Keywords: poker,card,game
Platform: UNKNOWN
Classifier: Development Status :: 2 - Pre-Alpha
Classifier: Intended Audience :: End Users/Desktop
Classifier: Topic :: Games/Entertainment :: Board Games
Classifier: License :: OSI Approved :: MIT License
Classifier: Programming Language :: Python :: 3
